django_embeddings/__init__.py
django_embeddings/admin.py
django_embeddings/apps.py
django_embeddings/models.py
django_embeddings/tasks.py
django_embeddings/tests.py
django_embeddings/urls.py
django_embeddings/utils.py
django_embeddings/validators.py
django_embeddings/views.py
django_embeddings/backends/__init__.py
django_embeddings/backends/base.py
django_embeddings/backends/st.py
sample_app/settings.py
sample_app/urls.py
sample_app/wsgi.py
django_embeddings-1.0.0.dist-info/METADATA
django_embeddings-1.0.0.dist-info/WHEEL
django_embeddings-1.0.0.dist-info/entry_points.txt
django_embeddings-1.0.0.dist-info/top_level.txt
django_embeddings-1.0.0.dist-info/RECORD
