Metadata-Version: 2.1
Name: django_embeddings
Version: 1.0.0
Summary: A Django application for embeddings
License: MIT License
Classifier: Development Status :: 5 - Production/Stable
Classifier: Framework :: Django
Classifier: Framework :: Django :: 3.2
Classifier: Framework :: Django :: 4.0
Classifier: Intended Audience :: Developers
Classifier: License :: OSI Approved :: MIT License
Classifier: Programming Language :: Python
Classifier: Programming Language :: Python :: 3.8
Classifier: Programming Language :: Python :: 3.9
Classifier: Programming Language :: Python :: 3.10
Requires-Python: >=3.8
Requires-Dist: Django
Requires-Dist: django-extensions
Requires-Dist: psycopg2
Requires-Dist: pgvector
Requires-Dist: django-simple-history
Requires-Dist: sentence-transformers
Requires-Dist: trafilatura
Requires-Dist: lxml_html_clean
Requires-Dist: beautifulsoup4
Requires-Dist: requests
Requires-Dist: django-environ
Requires-Dist: django-tasks
Requires-Dist: djangorestframework
